mtg_scryfall_grabber.py
mtg_scryfall_grabber-1.0.0.dist-info/METADATA
mtg_scryfall_grabber-1.0.0.dist-info/WHEEL
mtg_scryfall_grabber-1.0.0.dist-info/RECORD
