Metadata-Version: 2.1
Name: mtg_scryfall_grabber
Version: 1.0.0
Summary: MTG_Scryfall_Grabber (MSG) is a Python library/repository for scraping and organizing data from the Scryfall Rest-API.
Project-URL: Homepage, https://github.com/Contrastellar/mtg_scryfall_grabber
Project-URL: Bug Tracker, https://github.com/Contrastellar/mtg_scryfall_grabber/issues
Author-email: Gabriella Agathon <gjstimac@gmail.com>
Classifier: Operating System :: OS Independent
Classifier: Programming Language :: Python :: 3
Requires-Python: >=3.8
